bibliothek/__init__.py
bibliothek/toc/__init__.py
bibliothek/toc/note.py
bibliothek/toc/note_test.py
bibliothek/toc/toc.py
bibliothek/toc/toc_test.py
bibliothek/toc/util.py
bibliothek/toc/util_test.py
bibliothek-0.2.0.dist-info/LICENSE
bibliothek-0.2.0.dist-info/METADATA
bibliothek-0.2.0.dist-info/WHEEL
bibliothek-0.2.0.dist-info/top_level.txt
bibliothek-0.2.0.dist-info/RECORD
