Metadata-Version: 2.1
Name: bibliothek
Version: 0.2.0
Summary: Managing Markup Files
Home-page: https://github.com/ereyue/bibliothek
Author: ereyue
Author-email: python@ereyue.me
License: gpl-3.0
Platform: UNKNOWN
Classifier: Development Status :: 1 - Planning
Classifier: Programming Language :: Python :: 3.6
Classifier: Programming Language :: Python :: 3.7
Classifier: Programming Language :: Python :: 3.8
Classifier: Programming Language :: Python :: 3.9
Classifier: Programming Language :: Python :: 3 :: Only
Requires-Python: >=3.6
Requires-Dist: pyyaml
